README.txt
setup.py
ibio/__init__.py
ibio/__main__.py
ibio/messages.py
ibio/processes.py
ibio/vcf_processes.py
ibio.egg-info/PKG-INFO
ibio.egg-info/SOURCES.txt
ibio.egg-info/dependency_links.txt
ibio.egg-info/entry_points.txt
ibio.egg-info/not-zip-safe
ibio.egg-info/top_level.txt
ibio/bio/__init__.py
ibio/bio/bam.py
ibio/bio/bed.py
ibio/bio/file_class.py
ibio/bio/regions.py
ibio/bio/sequence.py
ibio/bio/tab.py
ibio/bio/vcf.py
ibio/cli/__init__.py
ibio/cli/task.py
ibio/dbs/__init__.py
ibio/dbs/ensembl_db.py
ibio/dbs/ucsc_db.py
ibio/tests/__init__.py
ibio/tests/test_basic_001.py
ibio/tests/test_databases_002.py
ibio/tests/test_variants_003.py