Metadata-Version: 1.2
Name: ibio
Version: 0.0.4
Summary: Package with bioinformatical utilities
Home-page: https://github.com/crispgc/ibio
Author: Cristian Perez
Author-email: Vilero89@gmail.com
License: GNU General Public License v3.0
Platform: UNKNOWN
Classifier: Development Status :: 3 - Alpha
Classifier: Programming Language :: Python :: 3
Requires-Python: >=3.6
